strava_gear/__init__.py
strava_gear/__main__.py
strava_gear/cli.py
strava_gear/cli_strava_offline.py
strava_gear/core.py
strava_gear/data.py
strava_gear/py.typed
strava_gear/report.py
strava_gear/input/__init__.py
strava_gear/input/activities.py
strava_gear/input/date.py
strava_gear/input/rules.py
strava_gear-1.1.0.dist-info/LICENSE
strava_gear-1.1.0.dist-info/METADATA
strava_gear-1.1.0.dist-info/WHEEL
strava_gear-1.1.0.dist-info/entry_points.txt
strava_gear-1.1.0.dist-info/top_level.txt
strava_gear-1.1.0.dist-info/RECORD
