Metadata-Version: 2.1
Name: strava-gear
Version: 1.1.0
Summary: Rule based tracker of gear and component wear primarily for Strava
Author-email: Tomáš Janoušek <tomi@nomi.cz>
License: MIT
Project-URL: Homepage, https://github.com/liskin/strava-gear
Classifier: Development Status :: 4 - Beta
Classifier: Environment :: Console
Classifier: License :: OSI Approved :: MIT License
Classifier: Operating System :: OS Independent
Classifier: Programming Language :: Python :: 3.8
Classifier: Programming Language :: Python :: 3.9
Classifier: Programming Language :: Python :: 3.10
Classifier: Programming Language :: Python :: 3.11
Classifier: Programming Language :: Python :: 3.12
Classifier: Topic :: Utilities
Requires-Python: ~=3.8
License-File: LICENSE
Requires-Dist: PyYAML
Requires-Dist: click ~=8.0
Requires-Dist: jsonschema
Requires-Dist: platformdirs >=2.1
Requires-Dist: python-dateutil >=2.7
Requires-Dist: tabulate
Requires-Dist: importlib-metadata ; python_version < "3.10"
Provides-Extra: dev
Requires-Dist: build >=0.7 ; extra == 'dev'
Requires-Dist: cram ; extra == 'dev'
Requires-Dist: flake8 >=3.7 ; extra == 'dev'
Requires-Dist: isort >=5.0 ; extra == 'dev'
Requires-Dist: mypy >=0.900 ; extra == 'dev'
Requires-Dist: twine ; extra == 'dev'
Requires-Dist: types-PyYAML ; extra == 'dev'
Requires-Dist: types-python-dateutil ; extra == 'dev'
Requires-Dist: types-tabulate ; extra == 'dev'
Provides-Extra: strava
Requires-Dist: strava-offline ~=1.0 ; extra == 'strava'
Provides-Extra: test
Requires-Dist: pytest ; extra == 'test'
